serialengine/__init__.py
ai.engine-0.0.1.dist-info/LICENSE
ai.engine-0.0.1.dist-info/METADATA
ai.engine-0.0.1.dist-info/WHEEL
ai.engine-0.0.1.dist-info/top_level.txt
ai.engine-0.0.1.dist-info/RECORD
