Metadata-Version: 2.1
Name: ai.engine
Version: 0.0.1
Summary: A universal serial communication engine
Home-page: https://github.com/0xJeremy/serial.engine
Author: Jeremy Kanovsky
Author-email: kanovsky.jeremy@gmail.com
License: UNKNOWN
Platform: UNKNOWN
Classifier: Programming Language :: Python :: 3
Classifier: License :: OSI Approved :: MIT License
